README.rst
setup.py
hgapi/__init__.py
hgapi/hgapi.py
hgapi/jython_in_practice.py
hgapi/testhgapi.py
hgapi.egg-info/PKG-INFO
hgapi.egg-info/SOURCES.txt
hgapi.egg-info/dependency_links.txt
hgapi.egg-info/top_level.txt