Metadata-Version: 1.1
Name: hgapi
Version: 1.7.2
Summary: Python API to Mercurial using the command-line interface
Home-page: https://bitbucket.org/haard/hgapi
Author: Fredrik Håård
Author-email: fredrik@haard.se
License: Do whatever you want, don't blame me
Keywords: mercurial api
Platform: UNKNOWN
Classifier: Development Status :: 5 - Production/Stable
Classifier: Intended Audience :: Developers
Classifier: License :: Freely Distributable
Classifier: License :: OSI Approved :: BSD License
Classifier: License :: OSI Approved :: MIT License
Classifier: Operating System :: OS Independent
Classifier: Programming Language :: Python :: 2
Classifier: Programming Language :: Python :: 2.7
Classifier: Programming Language :: Python :: 3
Classifier: Programming Language :: Python :: 3.2
Classifier: Programming Language :: Python :: 3.3
Classifier: Programming Language :: Python :: 3.4
Classifier: Topic :: Software Development :: Libraries
Classifier: Topic :: Software Development :: Version Control
